Metadata-Version: 1.0
Name: wxchatlib
Version: 0.0.3
Summary: 微信终端小程序
Home-page: UNKNOWN
Author: feichenxue
Author-email: 986024058@qq.com
License: UNKNOWN
Platform: UNKNOWN
